{
    "h": 600,
    "w": 600,
    "isVMem": 1,
    "isVSec": 1,
    "baseUrl": "https://cdn.picrew.me",
    "mkrType": 1,
    "title": "ぴくせるうさぎめーかー",
    "desc": "オリジナルのぴくせるうさぎをつくっちゃおう！₍ ᐢ. ̫ .ᐢ ₎\\r\\n\\r\\n🐰SNSのアイコンなどに使用する際は、\\r\\nプロフィールなどに \\r\\nアイコン：@murasakigezi \\r\\nと記載していただくと非常に励みになります〜！\\r\\n\\r\\n何か使用上で不安な事がございましたら、お気軽に作者のTwitter(@murasakigezi)にご連絡ください！\\r\\n\\r\\n⚠️非商用、商用で使用する場合は以下の文章を必ず\\r\\n　　記載してください！\\r\\n\\r\\nぴくせるうさぎめーかー 　作成者：ムラサキゲジゲジ \\r\\n作者のTwitter @murasakigezi\\r\\n\\r\\n　　この文章を記載する限り、このぴくせるうさぎメーカーで作成したイラストは\\r\\n　　完全に無料で使用する事が出来ます！\\r\\n\\r\\n⚠️NFT artにこのメーカーで作った画像を使用することを禁止します！\\r\\n\\r\\n🐰When using it for SNS icons, etc.,\\r\\n for profiles, etc.\\r\\nIcon: @murasakigezi\\r\\nIt will be very encouraging if you mention it!\\r\\n\\r\\nIf you have any concerns about using it, please feel free to contact the author's Twitter (@murasakigezi)!\\r\\n\\r\\n⚠️ For non-commercial and commercial use, \\r\\n　　write the following textPlease be sure to list it!\\r\\n\\r\\nPixel Rabbit Maker  Created by: Murasaki Gezi Gezi\\r\\nAuthor's Twitter @murasakigezi\\r\\n\\r\\n　　As long as this text is written, the illustrations created by this Pixel Rabbit Maker \\r\\n　　can be used completely free of charge.\\r\\n\\r\\n⚠️It is forbidden to use images made by this maker in NFT art!",
    "pList": [
        {
            "pId": 909373,
            "pType": 1,
            "pNm": "body",
            "isMenu": 1,
            "thumbUrl": "/app/image_maker/1028528/909373/p_4m19pOea5XANkKjy.png",
            "colorCnt": 12,
            "canMv": 0,
            "cpId": "l909373",
            "isRmv": 0,
            "x": 0,
            "y": 0,
            "angle": 0,
            "isMX": 0,
            "isMY": 0,
            "isRsiz": 0,
            "isRota": 0,
            "lyrs": [
                1014961
            ],
            "items": [
                {
                    "itmId": 2931090,
                    "thumbUrl": "/app/image_maker/1028528/909373/ii_wjH1vd7bfWZJbCGR.png",
                    "typeId": 1
                },
                {
                    "itmId": 2931296,
                    "thumbUrl": "/app/image_maker/1028528/909373/ii_Bi59TvhnJR01nK0d.png",
                    "typeId": 1
                },
                {
                    "itmId": 2931297,
                    "thumbUrl": "/app/image_maker/1028528/909373/ii_0oUqvpftnlfbKVjP.png",
                    "typeId": 1
                },
                {
                    "itmId": 2931298,
                    "thumbUrl": "/app/image_maker/1028528/909373/ii_J0FiEPTWop3FgxrT.png",
                    "typeId": 1
                },
                {
                    "itmId": 2931299,
                    "thumbUrl": "/app/image_maker/1028528/909373/ii_hBbSLxzEG2R7p3qV.png",
                    "typeId": 1
                },
                {
                    "itmId": 2931300,
                    "thumbUrl": "/app/image_maker/1028528/909373/ii_d0k4UNX4fnhp20qT.png",
                    "typeId": 1
                },
                {
                    "itmId": 2934470,
                    "thumbUrl": "/app/image_maker/1028528/909373/ii_9Rftdp8oVEbjoXcN.png",
                    "typeId": 1
                },
                {
                    "itmId": 2934471,
                    "thumbUrl": "/app/image_maker/1028528/909373/ii_6q11YqOKgykJKHdB.png",
                    "typeId": 1
                },
                {
                    "itmId": 2934472,
                    "thumbUrl": "/app/image_maker/1028528/909373/ii_wtTXgLpC5HSksWna.png",
                    "typeId": 1
                },
                {
                    "itmId": 2934696,
                    "thumbUrl": "/app/image_maker/1028528/909373/ii_bjdGKVm9lV0viyjk.png",
                    "typeId": 1
                },
                {
                    "itmId": 2934725,
                    "thumbUrl": "/app/image_maker/1028528/909373/ii_ews6BUVo1SeCgseE.png",
                    "typeId": 1
                },
                {
                    "itmId": 2934726,
                    "thumbUrl": "/app/image_maker/1028528/909373/ii_ztFrPR2cBjpY6pvW.png",
                    "typeId": 1
                },
                {
                    "itmId": 2935801,
                    "thumbUrl": "/app/image_maker/1028528/909373/ii_Vyt6xSOcbTb7xD8t.png",
                    "typeId": 1
                },
                {
                    "itmId": 2941597,
                    "thumbUrl": "/app/image_maker/1028528/909373/ii_S0n2PKUQG5i3O6fn.png",
                    "typeId": 1
                },
                {
                    "itmId": 2942059,
                    "thumbUrl": "/app/image_maker/1028528/909373/ii_TQU69bz7q8nLUtPu.png",
                    "typeId": 1
                },
                {
                    "itmId": 2942060,
                    "thumbUrl": "/app/image_maker/1028528/909373/ii_BZsk0UvcDoLfd8jW.png",
                    "typeId": 1
                },
                {
                    "itmId": 2942061,
                    "thumbUrl": "/app/image_maker/1028528/909373/ii_kJNJtuw8lMOUxJfQ.png",
                    "typeId": 1
                }
            ],
            "rules": [],
            "defItmId": 2931090
        },
        {
            "pId": 910856,
            "pType": 1,
            "pNm": "eyes",
            "isMenu": 1,
            "thumbUrl": "/app/image_maker/1028528/910856/p_EVhMNOVNgYQUluRr.png",
            "colorCnt": 9,
            "canMv": 0,
            "cpId": "l910856",
            "isRmv": 1,
            "x": 0,
            "y": 0,
            "angle": 0,
            "isMX": 0,
            "isMY": 0,
            "isRsiz": 0,
            "isRota": 0,
            "lyrs": [
                1016599
            ],
            "items": [
                {
                    "itmId": 2934480,
                    "thumbUrl": "/app/image_maker/1028528/910856/ii_l2bk3iUHijBrbTkq.png",
                    "typeId": 1
                },
                {
                    "itmId": 2934842,
                    "thumbUrl": "/app/image_maker/1028528/910856/ii_ynaaglpOdRISLBGF.png",
                    "typeId": 1
                },
                {
                    "itmId": 2934855,
                    "thumbUrl": "/app/image_maker/1028528/910856/ii_79wOZKhbyIJe2cjk.png",
                    "typeId": 1
                },
                {
                    "itmId": 2934856,
                    "thumbUrl": "/app/image_maker/1028528/910856/ii_g0p9qkQ0VSlfYza3.png",
                    "typeId": 1
                },
                {
                    "itmId": 2934889,
                    "thumbUrl": "/app/image_maker/1028528/910856/ii_yMTjXit1SxDHlmb8.png",
                    "typeId": 1
                },
                {
                    "itmId": 2934890,
                    "thumbUrl": "/app/image_maker/1028528/910856/ii_5oBmhWRPDlvViaOo.png",
                    "typeId": 1
                },
                {
                    "itmId": 2934911,
                    "thumbUrl": "/app/image_maker/1028528/910856/ii_1I9eJbPZm4Hxfeyu.png",
                    "typeId": 1
                },
                {
                    "itmId": 2934912,
                    "thumbUrl": "/app/image_maker/1028528/910856/ii_X047rH5RRof1WWnN.png",
                    "typeId": 1
                },
                {
                    "itmId": 2934969,
                    "thumbUrl": "/app/image_maker/1028528/910856/ii_96qGcCOLIAetW3TY.png",
                    "typeId": 1
                },
                {
                    "itmId": 2934970,
                    "thumbUrl": "/app/image_maker/1028528/910856/ii_oFP4vSgSvVNlkcWo.png",
                    "typeId": 1
                },
                {
                    "itmId": 2934973,
                    "thumbUrl": "/app/image_maker/1028528/910856/ii_l8OSpQKP3JKNZztX.png",
                    "typeId": 1
                },
                {
                    "itmId": 2934974,
                    "thumbUrl": "/app/image_maker/1028528/910856/ii_6BAIRbV4TrW4NtXu.png",
                    "typeId": 1
                },
                {
                    "itmId": 2935616,
                    "thumbUrl": "/app/image_maker/1028528/910856/ii_xI6A9KYWccFDwBQG.png",
                    "typeId": 1
                },
                {
                    "itmId": 2935617,
                    "thumbUrl": "/app/image_maker/1028528/910856/ii_jVu1Yy73nca6QSgk.png",
                    "typeId": 1
                },
                {
                    "itmId": 2935679,
                    "thumbUrl": "/app/image_maker/1028528/910856/ii_wLlphcRX5OuktckP.png",
                    "typeId": 1
                },
                {
                    "itmId": 2935680,
                    "thumbUrl": "/app/image_maker/1028528/910856/ii_QBDTPmQ0q60wcIVA.png",
                    "typeId": 1
                },
                {
                    "itmId": 2935703,
                    "thumbUrl": "/app/image_maker/1028528/910856/ii_vuIQPh19sizYZjkq.png",
                    "typeId": 1
                },
                {
                    "itmId": 2935704,
                    "thumbUrl": "/app/image_maker/1028528/910856/ii_8SzdJkcPmmQXCKxf.png",
                    "typeId": 1
                },
                {
                    "itmId": 2935762,
                    "thumbUrl": "/app/image_maker/1028528/910856/ii_1nEs8AALUZHnTo1Z.png",
                    "typeId": 1
                },
                {
                    "itmId": 2935763,
                    "thumbUrl": "/app/image_maker/1028528/910856/ii_0ykauCiUPrFxsbUl.png",
                    "typeId": 1
                },
                {
                    "itmId": 2942295,
                    "thumbUrl": "/app/image_maker/1028528/910856/ii_0MjbROVbRNDMQDFu.png",
                    "typeId": 1
                }
            ],
            "rules": [],
            "defItmId": 2934480
        },
        {
            "pId": 911155,
            "pType": 1,
            "pNm": "mouth",
            "isMenu": 1,
            "thumbUrl": "/app/image_maker/1028528/911155/p_TIBjEppLG6fUloas.png",
            "colorCnt": 1,
            "canMv": 0,
            "cpId": "l911155",
            "isRmv": 1,
            "x": 0,
            "y": 0,
            "angle": 0,
            "isMX": 0,
            "isMY": 0,
            "isRsiz": 0,
            "isRota": 0,
            "lyrs": [
                1016925
            ],
            "items": [
                {
                    "itmId": 2935020,
                    "thumbUrl": "/app/image_maker/1028528/911155/ii_Kc3AjngLSeBX4cKd.png",
                    "typeId": 1
                },
                {
                    "itmId": 2935853,
                    "thumbUrl": "/app/image_maker/1028528/911155/ii_IcOzbfdnvzzgShRO.png",
                    "typeId": 1
                },
                {
                    "itmId": 2935854,
                    "thumbUrl": "/app/image_maker/1028528/911155/ii_tao7jCTSimEgPXh0.png",
                    "typeId": 1
                },
                {
                    "itmId": 2935855,
                    "thumbUrl": "/app/image_maker/1028528/911155/ii_6Hh4pcd83xgQYdvq.png",
                    "typeId": 1
                },
                {
                    "itmId": 2935856,
                    "thumbUrl": "/app/image_maker/1028528/911155/ii_hQD1MmuPEW7s5H33.png",
                    "typeId": 1
                },
                {
                    "itmId": 2935857,
                    "thumbUrl": "/app/image_maker/1028528/911155/ii_8WHwE8jHzIWDZlN0.png",
                    "typeId": 1
                },
                {
                    "itmId": 2935858,
                    "thumbUrl": "/app/image_maker/1028528/911155/ii_wtDT5PvBKQEtfC18.png",
                    "typeId": 1
                },
                {
                    "itmId": 2935859,
                    "thumbUrl": "/app/image_maker/1028528/911155/ii_gNNF0hbZQb1saVLA.png",
                    "typeId": 1
                },
                {
                    "itmId": 2935860,
                    "thumbUrl": "/app/image_maker/1028528/911155/ii_ItJfs3R8idZqbV68.png",
                    "typeId": 1
                },
                {
                    "itmId": 2935861,
                    "thumbUrl": "/app/image_maker/1028528/911155/ii_bHyYzBxQ5ftcBWnZ.png",
                    "typeId": 1
                },
                {
                    "itmId": 2935862,
                    "thumbUrl": "/app/image_maker/1028528/911155/ii_deuCOc0puZEM3fx0.png",
                    "typeId": 1
                },
                {
                    "itmId": 2935868,
                    "thumbUrl": "/app/image_maker/1028528/911155/ii_0CdLn5x2xMYDmPND.png",
                    "typeId": 1
                },
                {
                    "itmId": 2935869,
                    "thumbUrl": "/app/image_maker/1028528/911155/ii_fd5c7LsEdqi4A2p3.png",
                    "typeId": 1
                },
                {
                    "itmId": 2935870,
                    "thumbUrl": "/app/image_maker/1028528/911155/ii_8DQIC82ASDHvIoET.png",
                    "typeId": 1
                },
                {
                    "itmId": 2935871,
                    "thumbUrl": "/app/image_maker/1028528/911155/ii_fw5FdIdvoOHiOyKh.png",
                    "typeId": 1
                },
                {
                    "itmId": 2935872,
                    "thumbUrl": "/app/image_maker/1028528/911155/ii_oIlrwFp0U4blGvTc.png",
                    "typeId": 1
                },
                {
                    "itmId": 2935887,
                    "thumbUrl": "/app/image_maker/1028528/911155/ii_oBcnoNQWL8wPKvQF.png",
                    "typeId": 1
                }
            ],
            "rules": [],
            "defItmId": 2935020
        },
        {
            "pId": 912396,
            "pType": 1,
            "pNm": "acceseries",
            "isMenu": 1,
            "thumbUrl": "/app/image_maker/1028528/912396/p_UXyZBvsr44fuaE2n.png",
            "colorCnt": 1,
            "canMv": 0,
            "cpId": "l912396",
            "isRmv": 1,
            "x": 0,
            "y": 0,
            "angle": 0,
            "isMX": 0,
            "isMY": 0,
            "isRsiz": 0,
            "isRota": 0,
            "lyrs": [
                1018338
            ],
            "items": [
                {
                    "itmId": 2938096,
                    "thumbUrl": "/app/image_maker/1028528/912396/ii_XXcCzB6l47goyZZR.png",
                    "typeId": 1
                },
                {
                    "itmId": 2938133,
                    "thumbUrl": "/app/image_maker/1028528/912396/ii_q3IVX3feKSDl34P0.png",
                    "typeId": 1
                },
                {
                    "itmId": 2938134,
                    "thumbUrl": "/app/image_maker/1028528/912396/ii_c7i6V36IvtjRQOYu.png",
                    "typeId": 1
                },
                {
                    "itmId": 2938135,
                    "thumbUrl": "/app/image_maker/1028528/912396/ii_lOONUjgaxVDGhHrw.png",
                    "typeId": 1
                },
                {
                    "itmId": 2938136,
                    "thumbUrl": "/app/image_maker/1028528/912396/ii_TCLnPrgHTPIhhMpW.png",
                    "typeId": 1
                },
                {
                    "itmId": 2938137,
                    "thumbUrl": "/app/image_maker/1028528/912396/ii_Piyn9mG3f4rwXCx7.png",
                    "typeId": 1
                },
                {
                    "itmId": 2938138,
                    "thumbUrl": "/app/image_maker/1028528/912396/ii_dhkEalZ1wIteYyWB.png",
                    "typeId": 1
                },
                {
                    "itmId": 2938139,
                    "thumbUrl": "/app/image_maker/1028528/912396/ii_YuGslcytLHGfNtkF.png",
                    "typeId": 1
                },
                {
                    "itmId": 2938140,
                    "thumbUrl": "/app/image_maker/1028528/912396/ii_b1vgGJtpTDQBobSW.png",
                    "typeId": 1
                },
                {
                    "itmId": 2938141,
                    "thumbUrl": "/app/image_maker/1028528/912396/ii_QSjvfOfGLXhP6n3c.png",
                    "typeId": 1
                },
                {
                    "itmId": 2938159,
                    "thumbUrl": "/app/image_maker/1028528/912396/ii_90tGsVlmWdgbMS1k.png",
                    "typeId": 1
                },
                {
                    "itmId": 2938160,
                    "thumbUrl": "/app/image_maker/1028528/912396/ii_uebSleFdNZAGEzJx.png",
                    "typeId": 1
                },
                {
                    "itmId": 2938161,
                    "thumbUrl": "/app/image_maker/1028528/912396/ii_d6CTECuHfWSagBti.png",
                    "typeId": 1
                },
                {
                    "itmId": 2938162,
                    "thumbUrl": "/app/image_maker/1028528/912396/ii_SkMC5bPTcRe7irZG.png",
                    "typeId": 1
                },
                {
                    "itmId": 2938163,
                    "thumbUrl": "/app/image_maker/1028528/912396/ii_Mle6idhnB9AnYVZL.png",
                    "typeId": 1
                },
                {
                    "itmId": 2938164,
                    "thumbUrl": "/app/image_maker/1028528/912396/ii_5HAUBabuA4ypZXYq.png",
                    "typeId": 1
                },
                {
                    "itmId": 2938165,
                    "thumbUrl": "/app/image_maker/1028528/912396/ii_aY6NF502O4KQHS77.png",
                    "typeId": 1
                },
                {
                    "itmId": 2938166,
                    "thumbUrl": "/app/image_maker/1028528/912396/ii_xCwOuEywAF9vrWsV.png",
                    "typeId": 1
                },
                {
                    "itmId": 2938167,
                    "thumbUrl": "/app/image_maker/1028528/912396/ii_35BgeSB30LtHl4aM.png",
                    "typeId": 1
                },
                {
                    "itmId": 2938168,
                    "thumbUrl": "/app/image_maker/1028528/912396/ii_b9HwRUVEGCx1R5Pp.png",
                    "typeId": 1
                },
                {
                    "itmId": 2938191,
                    "thumbUrl": "/app/image_maker/1028528/912396/ii_KtVojOQxPmNyCpvp.png",
                    "typeId": 1
                },
                {
                    "itmId": 2938192,
                    "thumbUrl": "/app/image_maker/1028528/912396/ii_5ULKu3kLUGJlzm7T.png",
                    "typeId": 1
                },
                {
                    "itmId": 2938193,
                    "thumbUrl": "/app/image_maker/1028528/912396/ii_Obvaho73tsTmYmoq.png",
                    "typeId": 1
                },
                {
                    "itmId": 2938194,
                    "thumbUrl": "/app/image_maker/1028528/912396/ii_GQgmZAuv5pi4oAMW.png",
                    "typeId": 1
                },
                {
                    "itmId": 2938195,
                    "thumbUrl": "/app/image_maker/1028528/912396/ii_y8EuoJP0CcagEGi7.png",
                    "typeId": 1
                },
                {
                    "itmId": 2938196,
                    "thumbUrl": "/app/image_maker/1028528/912396/ii_bM5Xxw3wwSKQ9bXl.png",
                    "typeId": 1
                },
                {
                    "itmId": 2938197,
                    "thumbUrl": "/app/image_maker/1028528/912396/ii_7oVzVvLgrxUhQxQn.png",
                    "typeId": 1
                },
                {
                    "itmId": 2938198,
                    "thumbUrl": "/app/image_maker/1028528/912396/ii_rGxq2GbYHYEemM5y.png",
                    "typeId": 1
                },
                {
                    "itmId": 2938199,
                    "thumbUrl": "/app/image_maker/1028528/912396/ii_9La3iydS7FrJcLKW.png",
                    "typeId": 1
                },
                {
                    "itmId": 2938200,
                    "thumbUrl": "/app/image_maker/1028528/912396/ii_GfH8VmvdOZs5vZrz.png",
                    "typeId": 1
                },
                {
                    "itmId": 2938277,
                    "thumbUrl": "/app/image_maker/1028528/912396/ii_FtrsDx5hjNbYUTL2.png",
                    "typeId": 1
                },
                {
                    "itmId": 2938278,
                    "thumbUrl": "/app/image_maker/1028528/912396/ii_L2291OlJq2H4A9uX.png",
                    "typeId": 1
                },
                {
                    "itmId": 2938279,
                    "thumbUrl": "/app/image_maker/1028528/912396/ii_IWTK3KJMTj2UFTQH.png",
                    "typeId": 1
                },
                {
                    "itmId": 2938280,
                    "thumbUrl": "/app/image_maker/1028528/912396/ii_rblflUqQI5ArDSCf.png",
                    "typeId": 1
                },
                {
                    "itmId": 2938281,
                    "thumbUrl": "/app/image_maker/1028528/912396/ii_YREYtm67MvDSRnLn.png",
                    "typeId": 1
                },
                {
                    "itmId": 2938282,
                    "thumbUrl": "/app/image_maker/1028528/912396/ii_SUN6H4bi8LFtgVZj.png",
                    "typeId": 1
                },
                {
                    "itmId": 2938283,
                    "thumbUrl": "/app/image_maker/1028528/912396/ii_IdcXdaAioeG8Jakv.png",
                    "typeId": 1
                },
                {
                    "itmId": 2938284,
                    "thumbUrl": "/app/image_maker/1028528/912396/ii_oG5TcHMguj84QPKD.png",
                    "typeId": 1
                },
                {
                    "itmId": 2938285,
                    "thumbUrl": "/app/image_maker/1028528/912396/ii_nMpEt2OPGJnmX04D.png",
                    "typeId": 1
                },
                {
                    "itmId": 2938286,
                    "thumbUrl": "/app/image_maker/1028528/912396/ii_Qsv69qvGDlrWMrIE.png",
                    "typeId": 1
                },
                {
                    "itmId": 2938329,
                    "thumbUrl": "/app/image_maker/1028528/912396/ii_NTthzaiAIQPIhjeq.png",
                    "typeId": 1
                },
                {
                    "itmId": 2938330,
                    "thumbUrl": "/app/image_maker/1028528/912396/ii_ZGjqaVPThixvYLHJ.png",
                    "typeId": 1
                },
                {
                    "itmId": 2938331,
                    "thumbUrl": "/app/image_maker/1028528/912396/ii_1umzAih3YK2cmFiE.png",
                    "typeId": 1
                },
                {
                    "itmId": 2938332,
                    "thumbUrl": "/app/image_maker/1028528/912396/ii_tOf648LSuru4YG2H.png",
                    "typeId": 1
                },
                {
                    "itmId": 2938333,
                    "thumbUrl": "/app/image_maker/1028528/912396/ii_YVIrg17crgd9ux1M.png",
                    "typeId": 1
                },
                {
                    "itmId": 2938334,
                    "thumbUrl": "/app/image_maker/1028528/912396/ii_K9Szj3CE4yqOxmmw.png",
                    "typeId": 1
                },
                {
                    "itmId": 2938335,
                    "thumbUrl": "/app/image_maker/1028528/912396/ii_eaTd4iRDCxuEt5dj.png",
                    "typeId": 1
                },
                {
                    "itmId": 2938336,
                    "thumbUrl": "/app/image_maker/1028528/912396/ii_6EljhS9kPtZmh2EP.png",
                    "typeId": 1
                },
                {
                    "itmId": 2938337,
                    "thumbUrl": "/app/image_maker/1028528/912396/ii_bQ5A29YuJyWOq7Li.png",
                    "typeId": 1
                },
                {
                    "itmId": 2938338,
                    "thumbUrl": "/app/image_maker/1028528/912396/ii_hOjT6JN5kP7DI1nY.png",
                    "typeId": 1
                },
                {
                    "itmId": 2942224,
                    "thumbUrl": "/app/image_maker/1028528/912396/ii_DGmqrmlhsDaQFWIS.png",
                    "typeId": 1
                },
                {
                    "itmId": 2942225,
                    "thumbUrl": "/app/image_maker/1028528/912396/ii_UwHj0pl1UCrt8FaO.png",
                    "typeId": 1
                },
                {
                    "itmId": 2942226,
                    "thumbUrl": "/app/image_maker/1028528/912396/ii_pqhojr9mwXiCpiFR.png",
                    "typeId": 1
                },
                {
                    "itmId": 2942227,
                    "thumbUrl": "/app/image_maker/1028528/912396/ii_TsotiJ2Sg9KMw01h.png",
                    "typeId": 1
                },
                {
                    "itmId": 2942228,
                    "thumbUrl": "/app/image_maker/1028528/912396/ii_9zHnUagk8rpsa3L7.png",
                    "typeId": 1
                }
            ],
            "rules": [],
            "defItmId": 2938096
        },
        {
            "pId": 912400,
            "pType": 1,
            "pNm": "hat",
            "isMenu": 1,
            "thumbUrl": "/app/image_maker/1028528/912400/p_BSaXJHdeJy8ureZi.png",
            "colorCnt": 1,
            "canMv": 0,
            "cpId": "l912400",
            "isRmv": 1,
            "x": 0,
            "y": 0,
            "angle": 0,
            "isMX": 0,
            "isMY": 0,
            "isRsiz": 0,
            "isRota": 0,
            "lyrs": [
                1018342
            ],
            "items": [
                {
                    "itmId": 2938101,
                    "thumbUrl": "/app/image_maker/1028528/912400/ii_Xkrvn38lFdZgWNUR.png",
                    "typeId": 1
                },
                {
                    "itmId": 2938467,
                    "thumbUrl": "/app/image_maker/1028528/912400/ii_WKOrt7eiiuuPz6v4.png",
                    "typeId": 1
                },
                {
                    "itmId": 2938468,
                    "thumbUrl": "/app/image_maker/1028528/912400/ii_1Sc1QAR9jr2a4V63.png",
                    "typeId": 1
                },
                {
                    "itmId": 2938469,
                    "thumbUrl": "/app/image_maker/1028528/912400/ii_UI3W3fdlyvldNfWl.png",
                    "typeId": 1
                },
                {
                    "itmId": 2938470,
                    "thumbUrl": "/app/image_maker/1028528/912400/ii_7GrbsNRHz4maIt7L.png",
                    "typeId": 1
                },
                {
                    "itmId": 2938471,
                    "thumbUrl": "/app/image_maker/1028528/912400/ii_LSkB0ZmZSzwC8KrN.png",
                    "typeId": 1
                },
                {
                    "itmId": 2938472,
                    "thumbUrl": "/app/image_maker/1028528/912400/ii_ke2LeyUPmOKzGBMt.png",
                    "typeId": 1
                },
                {
                    "itmId": 2938473,
                    "thumbUrl": "/app/image_maker/1028528/912400/ii_uvOnvBy2gM1lmDhy.png",
                    "typeId": 1
                },
                {
                    "itmId": 2938474,
                    "thumbUrl": "/app/image_maker/1028528/912400/ii_VQUMEILIjz6oCL9D.png",
                    "typeId": 1
                },
                {
                    "itmId": 2938475,
                    "thumbUrl": "/app/image_maker/1028528/912400/ii_Ou13wXLYxD0QvTdR.png",
                    "typeId": 1
                },
                {
                    "itmId": 2938489,
                    "thumbUrl": "/app/image_maker/1028528/912400/ii_JQF9JsCMEFrSHUGq.png",
                    "typeId": 1
                },
                {
                    "itmId": 2938490,
                    "thumbUrl": "/app/image_maker/1028528/912400/ii_htXnEHNbnKR7NYYH.png",
                    "typeId": 1
                },
                {
                    "itmId": 2938491,
                    "thumbUrl": "/app/image_maker/1028528/912400/ii_kUxuKgmeRmkNw9xu.png",
                    "typeId": 1
                },
                {
                    "itmId": 2938492,
                    "thumbUrl": "/app/image_maker/1028528/912400/ii_zzJhcYQO5DvDcFpy.png",
                    "typeId": 1
                },
                {
                    "itmId": 2938493,
                    "thumbUrl": "/app/image_maker/1028528/912400/ii_muzCzfaxlZoGGQ5M.png",
                    "typeId": 1
                },
                {
                    "itmId": 2938494,
                    "thumbUrl": "/app/image_maker/1028528/912400/ii_9dovvO03jvZzWdu8.png",
                    "typeId": 1
                },
                {
                    "itmId": 2938495,
                    "thumbUrl": "/app/image_maker/1028528/912400/ii_CpFYWPdFOXmu5DLq.png",
                    "typeId": 1
                },
                {
                    "itmId": 2938496,
                    "thumbUrl": "/app/image_maker/1028528/912400/ii_djnwGglDe71OM2cx.png",
                    "typeId": 1
                },
                {
                    "itmId": 2938497,
                    "thumbUrl": "/app/image_maker/1028528/912400/ii_KrXcITdLVGTriozM.png",
                    "typeId": 1
                },
                {
                    "itmId": 2938498,
                    "thumbUrl": "/app/image_maker/1028528/912400/ii_c0sg2oQ15h6De9ul.png",
                    "typeId": 1
                },
                {
                    "itmId": 2940796,
                    "thumbUrl": "/app/image_maker/1028528/912400/ii_qheHUssmFNvPncpt.png",
                    "typeId": 1
                },
                {
                    "itmId": 2940797,
                    "thumbUrl": "/app/image_maker/1028528/912400/ii_iGGmZURO4Hd3dx7i.png",
                    "typeId": 1
                },
                {
                    "itmId": 2940798,
                    "thumbUrl": "/app/image_maker/1028528/912400/ii_q2HgBWDwkHbKul4a.png",
                    "typeId": 1
                },
                {
                    "itmId": 2940799,
                    "thumbUrl": "/app/image_maker/1028528/912400/ii_Qjs7rUOp3T5CxBhB.png",
                    "typeId": 1
                },
                {
                    "itmId": 2940800,
                    "thumbUrl": "/app/image_maker/1028528/912400/ii_pJSrxUPI01ppQzE7.png",
                    "typeId": 1
                },
                {
                    "itmId": 2940801,
                    "thumbUrl": "/app/image_maker/1028528/912400/ii_QfnlSN8egbzHkZUG.png",
                    "typeId": 1
                },
                {
                    "itmId": 2940802,
                    "thumbUrl": "/app/image_maker/1028528/912400/ii_4RqiIv4pgs9771LY.png",
                    "typeId": 1
                },
                {
                    "itmId": 2940803,
                    "thumbUrl": "/app/image_maker/1028528/912400/ii_zFqUt9bQhMCH4jZE.png",
                    "typeId": 1
                },
                {
                    "itmId": 2940804,
                    "thumbUrl": "/app/image_maker/1028528/912400/ii_sMmErAeivvCCQNLx.png",
                    "typeId": 1
                },
                {
                    "itmId": 2940805,
                    "thumbUrl": "/app/image_maker/1028528/912400/ii_tHV9XsIyaW7BffEw.png",
                    "typeId": 1
                },
                {
                    "itmId": 2940817,
                    "thumbUrl": "/app/image_maker/1028528/912400/ii_ul5LelaTj6irr9CZ.png",
                    "typeId": 1
                },
                {
                    "itmId": 2940818,
                    "thumbUrl": "/app/image_maker/1028528/912400/ii_yWaT4L3fHuN0dqrs.png",
                    "typeId": 1
                },
                {
                    "itmId": 2940819,
                    "thumbUrl": "/app/image_maker/1028528/912400/ii_AljUcTIqp0isYP1u.png",
                    "typeId": 1
                },
                {
                    "itmId": 2940820,
                    "thumbUrl": "/app/image_maker/1028528/912400/ii_43VPGrEFpk7U27Wd.png",
                    "typeId": 1
                },
                {
                    "itmId": 2940821,
                    "thumbUrl": "/app/image_maker/1028528/912400/ii_E0K4QrVyk3t4BU7R.png",
                    "typeId": 1
                },
                {
                    "itmId": 2940822,
                    "thumbUrl": "/app/image_maker/1028528/912400/ii_kpwiRdgMWOQZLYjM.png",
                    "typeId": 1
                },
                {
                    "itmId": 2940823,
                    "thumbUrl": "/app/image_maker/1028528/912400/ii_eBOPUVrC4vQQ91Hi.png",
                    "typeId": 1
                },
                {
                    "itmId": 2940824,
                    "thumbUrl": "/app/image_maker/1028528/912400/ii_moi0SzXeL2bA9YMI.png",
                    "typeId": 1
                },
                {
                    "itmId": 2940825,
                    "thumbUrl": "/app/image_maker/1028528/912400/ii_yGe2xm4qFm4WNdIF.png",
                    "typeId": 1
                },
                {
                    "itmId": 2940826,
                    "thumbUrl": "/app/image_maker/1028528/912400/ii_rRUSUgRCrXhIKp4M.png",
                    "typeId": 1
                },
                {
                    "itmId": 2940981,
                    "thumbUrl": "/app/image_maker/1028528/912400/ii_7Pjn8fJ2IvJL9ya8.png",
                    "typeId": 1
                },
                {
                    "itmId": 2940982,
                    "thumbUrl": "/app/image_maker/1028528/912400/ii_jItoHMH3SBkNGr5S.png",
                    "typeId": 1
                },
                {
                    "itmId": 2940983,
                    "thumbUrl": "/app/image_maker/1028528/912400/ii_4O20cjCKBEXdlqTz.png",
                    "typeId": 1
                },
                {
                    "itmId": 2940984,
                    "thumbUrl": "/app/image_maker/1028528/912400/ii_l9GFk0Tg2UQBqlaU.png",
                    "typeId": 1
                },
                {
                    "itmId": 2940985,
                    "thumbUrl": "/app/image_maker/1028528/912400/ii_adKD3O7Es8yADww2.png",
                    "typeId": 1
                },
                {
                    "itmId": 2940986,
                    "thumbUrl": "/app/image_maker/1028528/912400/ii_AFGvPMzP7p5pXcQJ.png",
                    "typeId": 1
                },
                {
                    "itmId": 2940987,
                    "thumbUrl": "/app/image_maker/1028528/912400/ii_3rwXQwIU1TMNrKwB.png",
                    "typeId": 1
                },
                {
                    "itmId": 2940988,
                    "thumbUrl": "/app/image_maker/1028528/912400/ii_Zv2Ial89Gc7D1BvG.png",
                    "typeId": 1
                },
                {
                    "itmId": 2940989,
                    "thumbUrl": "/app/image_maker/1028528/912400/ii_HJbXq07gMhU8pc9S.png",
                    "typeId": 1
                },
                {
                    "itmId": 2940990,
                    "thumbUrl": "/app/image_maker/1028528/912400/ii_p5hxWoH56yIB5N5Z.png",
                    "typeId": 1
                },
                {
                    "itmId": 2940996,
                    "thumbUrl": "/app/image_maker/1028528/912400/ii_Rhv7Xm8XN5rXX4aE.png",
                    "typeId": 1
                },
                {
                    "itmId": 2940997,
                    "thumbUrl": "/app/image_maker/1028528/912400/ii_d0eJnl88OElnSImF.png",
                    "typeId": 1
                },
                {
                    "itmId": 2940998,
                    "thumbUrl": "/app/image_maker/1028528/912400/ii_GjaRCatJykIunui4.png",
                    "typeId": 1
                },
                {
                    "itmId": 2940999,
                    "thumbUrl": "/app/image_maker/1028528/912400/ii_FSGkgIz0PAcLEcmK.png",
                    "typeId": 1
                },
                {
                    "itmId": 2941000,
                    "thumbUrl": "/app/image_maker/1028528/912400/ii_aGCt18k5xdaPEuhm.png",
                    "typeId": 1
                },
                {
                    "itmId": 2941001,
                    "thumbUrl": "/app/image_maker/1028528/912400/ii_wfyRNefu3qzd7LBS.png",
                    "typeId": 1
                },
                {
                    "itmId": 2941002,
                    "thumbUrl": "/app/image_maker/1028528/912400/ii_t8CTUiLigL4dA8iw.png",
                    "typeId": 1
                },
                {
                    "itmId": 2941003,
                    "thumbUrl": "/app/image_maker/1028528/912400/ii_PCPjCUongINzl0ri.png",
                    "typeId": 1
                },
                {
                    "itmId": 2941004,
                    "thumbUrl": "/app/image_maker/1028528/912400/ii_uBSyjhfCBX3GYlsX.png",
                    "typeId": 1
                },
                {
                    "itmId": 2941005,
                    "thumbUrl": "/app/image_maker/1028528/912400/ii_RhnhYgcNyUysDkvc.png",
                    "typeId": 1
                },
                {
                    "itmId": 2942229,
                    "thumbUrl": "/app/image_maker/1028528/912400/ii_fJdwEFJ8xMLykYFO.png",
                    "typeId": 1
                },
                {
                    "itmId": 2942230,
                    "thumbUrl": "/app/image_maker/1028528/912400/ii_gdnKyjQJwPrZTgqo.png",
                    "typeId": 1
                },
                {
                    "itmId": 2942231,
                    "thumbUrl": "/app/image_maker/1028528/912400/ii_OP861XyYdXZwEjyq.png",
                    "typeId": 1
                },
                {
                    "itmId": 2942232,
                    "thumbUrl": "/app/image_maker/1028528/912400/ii_hk0JluloEIvRM5aw.png",
                    "typeId": 1
                },
                {
                    "itmId": 2942233,
                    "thumbUrl": "/app/image_maker/1028528/912400/ii_VoirWRg6CYjAXzrA.png",
                    "typeId": 1
                }
            ],
            "rules": [],
            "defItmId": 0
        },
        {
            "pId": 912398,
            "pType": 1,
            "pNm": "effect",
            "isMenu": 1,
            "thumbUrl": "/app/image_maker/1028528/912398/p_1en8lFBe16fA5nIJ.png",
            "colorCnt": 1,
            "canMv": 0,
            "cpId": "l912398",
            "isRmv": 1,
            "x": 0,
            "y": 0,
            "angle": 0,
            "isMX": 0,
            "isMY": 0,
            "isRsiz": 0,
            "isRota": 0,
            "lyrs": [
                1018340
            ],
            "items": [
                {
                    "itmId": 2938099,
                    "thumbUrl": "/app/image_maker/1028528/912398/ii_DSOfJ6MiKLfb6TgM.png",
                    "typeId": 1
                },
                {
                    "itmId": 2941041,
                    "thumbUrl": "/app/image_maker/1028528/912398/ii_re4taInpqhyrakcY.png",
                    "typeId": 1
                },
                {
                    "itmId": 2941042,
                    "thumbUrl": "/app/image_maker/1028528/912398/ii_8UYWg1rN1zEj931I.png",
                    "typeId": 1
                },
                {
                    "itmId": 2941043,
                    "thumbUrl": "/app/image_maker/1028528/912398/ii_nT81uUsWkxTrNJhS.png",
                    "typeId": 1
                },
                {
                    "itmId": 2941044,
                    "thumbUrl": "/app/image_maker/1028528/912398/ii_bzf6SLNb95Lbkcrb.png",
                    "typeId": 1
                },
                {
                    "itmId": 2941045,
                    "thumbUrl": "/app/image_maker/1028528/912398/ii_oq6LEpqFTUH1KcBw.png",
                    "typeId": 1
                },
                {
                    "itmId": 2941046,
                    "thumbUrl": "/app/image_maker/1028528/912398/ii_58jMa6gGJkvmFsK9.png",
                    "typeId": 1
                },
                {
                    "itmId": 2941047,
                    "thumbUrl": "/app/image_maker/1028528/912398/ii_o4t2Wnxrc53pAqPh.png",
                    "typeId": 1
                },
                {
                    "itmId": 2941048,
                    "thumbUrl": "/app/image_maker/1028528/912398/ii_yiZJTmYxsHeH1DtV.png",
                    "typeId": 1
                },
                {
                    "itmId": 2941049,
                    "thumbUrl": "/app/image_maker/1028528/912398/ii_QnCUxmobwqh9KhKR.png",
                    "typeId": 1
                },
                {
                    "itmId": 2941052,
                    "thumbUrl": "/app/image_maker/1028528/912398/ii_lHP68rrcU7XxDwG2.png",
                    "typeId": 1
                },
                {
                    "itmId": 2941053,
                    "thumbUrl": "/app/image_maker/1028528/912398/ii_V63qTvlHMppHQ8ry.png",
                    "typeId": 1
                },
                {
                    "itmId": 2941054,
                    "thumbUrl": "/app/image_maker/1028528/912398/ii_1ThaqoFlGUivVXkT.png",
                    "typeId": 1
                },
                {
                    "itmId": 2941055,
                    "thumbUrl": "/app/image_maker/1028528/912398/ii_ByP8VGoKoLMSeDQ9.png",
                    "typeId": 1
                },
                {
                    "itmId": 2941056,
                    "thumbUrl": "/app/image_maker/1028528/912398/ii_i5G3uy3YyVycTwE6.png",
                    "typeId": 1
                },
                {
                    "itmId": 2941057,
                    "thumbUrl": "/app/image_maker/1028528/912398/ii_IvoEsOX6tTilXnDG.png",
                    "typeId": 1
                },
                {
                    "itmId": 2941058,
                    "thumbUrl": "/app/image_maker/1028528/912398/ii_U1x9ZNyLyIiA13lZ.png",
                    "typeId": 1
                },
                {
                    "itmId": 2941059,
                    "thumbUrl": "/app/image_maker/1028528/912398/ii_c2wmzPPoIv6YRwqs.png",
                    "typeId": 1
                },
                {
                    "itmId": 2941060,
                    "thumbUrl": "/app/image_maker/1028528/912398/ii_5lbj0Oue05FvEzb1.png",
                    "typeId": 1
                },
                {
                    "itmId": 2941061,
                    "thumbUrl": "/app/image_maker/1028528/912398/ii_z9NVf0TY2FGZDZyx.png",
                    "typeId": 1
                },
                {
                    "itmId": 2941209,
                    "thumbUrl": "/app/image_maker/1028528/912398/ii_kcOBNsHbucAEeZiG.png",
                    "typeId": 1
                },
                {
                    "itmId": 2941210,
                    "thumbUrl": "/app/image_maker/1028528/912398/ii_NC3pjSoaOqPfan2H.png",
                    "typeId": 1
                },
                {
                    "itmId": 2941211,
                    "thumbUrl": "/app/image_maker/1028528/912398/ii_ScaDcOFm5s0KayvO.png",
                    "typeId": 1
                },
                {
                    "itmId": 2941212,
                    "thumbUrl": "/app/image_maker/1028528/912398/ii_TO3ArWP5Bqp4rSAq.png",
                    "typeId": 1
                },
                {
                    "itmId": 2941213,
                    "thumbUrl": "/app/image_maker/1028528/912398/ii_vU7BhEXP9G4qgil0.png",
                    "typeId": 1
                },
                {
                    "itmId": 2941214,
                    "thumbUrl": "/app/image_maker/1028528/912398/ii_V6PptAbsiszUDrzz.png",
                    "typeId": 1
                },
                {
                    "itmId": 2941215,
                    "thumbUrl": "/app/image_maker/1028528/912398/ii_qTxnwneQFBuZEiIf.png",
                    "typeId": 1
                },
                {
                    "itmId": 2941216,
                    "thumbUrl": "/app/image_maker/1028528/912398/ii_F4uTLKT8ypRKdd64.png",
                    "typeId": 1
                },
                {
                    "itmId": 2941217,
                    "thumbUrl": "/app/image_maker/1028528/912398/ii_6TXIYCuybi82gkqL.png",
                    "typeId": 1
                },
                {
                    "itmId": 2941218,
                    "thumbUrl": "/app/image_maker/1028528/912398/ii_iLOVu9BGE5e8rY0e.png",
                    "typeId": 1
                },
                {
                    "itmId": 2941219,
                    "thumbUrl": "/app/image_maker/1028528/912398/ii_AyjAzY9Z40ASktI6.png",
                    "typeId": 1
                },
                {
                    "itmId": 2941220,
                    "thumbUrl": "/app/image_maker/1028528/912398/ii_GkulLs1uYXVeo4ef.png",
                    "typeId": 1
                },
                {
                    "itmId": 2941221,
                    "thumbUrl": "/app/image_maker/1028528/912398/ii_8y4CWO7hZuwvrVG6.png",
                    "typeId": 1
                },
                {
                    "itmId": 2941222,
                    "thumbUrl": "/app/image_maker/1028528/912398/ii_UhSJq4XTjo4qLeOQ.png",
                    "typeId": 1
                },
                {
                    "itmId": 2941223,
                    "thumbUrl": "/app/image_maker/1028528/912398/ii_r5R3FMw5R2OP5maI.png",
                    "typeId": 1
                },
                {
                    "itmId": 2941224,
                    "thumbUrl": "/app/image_maker/1028528/912398/ii_QSFnPkhTs7hFYMQC.png",
                    "typeId": 1
                },
                {
                    "itmId": 2941225,
                    "thumbUrl": "/app/image_maker/1028528/912398/ii_Z2ga4O98A4NgKBr5.png",
                    "typeId": 1
                },
                {
                    "itmId": 2941226,
                    "thumbUrl": "/app/image_maker/1028528/912398/ii_vzniBEfw9a5a4D2T.png",
                    "typeId": 1
                },
                {
                    "itmId": 2941227,
                    "thumbUrl": "/app/image_maker/1028528/912398/ii_kSoDs06v3xQJyxlJ.png",
                    "typeId": 1
                },
                {
                    "itmId": 2941228,
                    "thumbUrl": "/app/image_maker/1028528/912398/ii_20Jv0N1sJuoV4ZyL.png",
                    "typeId": 1
                },
                {
                    "itmId": 2941249,
                    "thumbUrl": "/app/image_maker/1028528/912398/ii_107ifj5dazsgXNpu.png",
                    "typeId": 1
                },
                {
                    "itmId": 2941250,
                    "thumbUrl": "/app/image_maker/1028528/912398/ii_AyLVsPiIc4aGAciL.png",
                    "typeId": 1
                },
                {
                    "itmId": 2941251,
                    "thumbUrl": "/app/image_maker/1028528/912398/ii_2lpFJ1bERNDAYeJ9.png",
                    "typeId": 1
                },
                {
                    "itmId": 2941252,
                    "thumbUrl": "/app/image_maker/1028528/912398/ii_aVUa3WQLjtIVgYDa.png",
                    "typeId": 1
                },
                {
                    "itmId": 2941253,
                    "thumbUrl": "/app/image_maker/1028528/912398/ii_8ZeQKrAAhmZcNWYN.png",
                    "typeId": 1
                },
                {
                    "itmId": 2941254,
                    "thumbUrl": "/app/image_maker/1028528/912398/ii_X19fBmg7SQUr8tU8.png",
                    "typeId": 1
                },
                {
                    "itmId": 2941255,
                    "thumbUrl": "/app/image_maker/1028528/912398/ii_NKrvexsvvkTyQmhA.png",
                    "typeId": 1
                },
                {
                    "itmId": 2941256,
                    "thumbUrl": "/app/image_maker/1028528/912398/ii_TE4L44qKJMBm2EKz.png",
                    "typeId": 1
                },
                {
                    "itmId": 2941257,
                    "thumbUrl": "/app/image_maker/1028528/912398/ii_wXjkuqKUJrusPC5P.png",
                    "typeId": 1
                },
                {
                    "itmId": 2941258,
                    "thumbUrl": "/app/image_maker/1028528/912398/ii_q8NrGxx1oZEcxOQS.png",
                    "typeId": 1
                },
                {
                    "itmId": 2941534,
                    "thumbUrl": "/app/image_maker/1028528/912398/ii_csnfKVIGGYURKUnY.png",
                    "typeId": 1
                },
                {
                    "itmId": 2941535,
                    "thumbUrl": "/app/image_maker/1028528/912398/ii_1aeQ9hMVDOu0Q3dp.png",
                    "typeId": 1
                },
                {
                    "itmId": 2941536,
                    "thumbUrl": "/app/image_maker/1028528/912398/ii_9RWQkfZIFrST8Gg8.png",
                    "typeId": 1
                },
                {
                    "itmId": 2941537,
                    "thumbUrl": "/app/image_maker/1028528/912398/ii_QyvzwKE6UBJPM2EW.png",
                    "typeId": 1
                },
                {
                    "itmId": 2941538,
                    "thumbUrl": "/app/image_maker/1028528/912398/ii_N9GnkHABAkI4wa5m.png",
                    "typeId": 1
                },
                {
                    "itmId": 2941539,
                    "thumbUrl": "/app/image_maker/1028528/912398/ii_ndvixyleTAL8VR7s.png",
                    "typeId": 1
                },
                {
                    "itmId": 2941540,
                    "thumbUrl": "/app/image_maker/1028528/912398/ii_BMnOAX8PTCcDMinI.png",
                    "typeId": 1
                },
                {
                    "itmId": 2941541,
                    "thumbUrl": "/app/image_maker/1028528/912398/ii_VvtEh6KxUhw0sfL1.png",
                    "typeId": 1
                },
                {
                    "itmId": 2941542,
                    "thumbUrl": "/app/image_maker/1028528/912398/ii_yWJs8dIjaecabspH.png",
                    "typeId": 1
                },
                {
                    "itmId": 2941543,
                    "thumbUrl": "/app/image_maker/1028528/912398/ii_VfvvydRS16k9Qmfi.png",
                    "typeId": 1
                }
            ],
            "rules": [],
            "defItmId": 2938099
        },
        {
            "pId": 911614,
            "pType": 1,
            "pNm": "background",
            "isMenu": 1,
            "thumbUrl": "/app/image_maker/1028528/911614/p_1D8HuEBfxbkJwCqu.png",
            "colorCnt": 1,
            "canMv": 0,
            "cpId": "l911614",
            "isRmv": 1,
            "x": 0,
            "y": 0,
            "angle": 0,
            "isMX": 0,
            "isMY": 0,
            "isRsiz": 0,
            "isRota": 0,
            "lyrs": [
                1017458
            ],
            "items": [
                {
                    "itmId": 2935947,
                    "thumbUrl": "/app/image_maker/1028528/911614/ii_ZFxo2qHr1P98YO3t.png",
                    "typeId": 1
                },
                {
                    "itmId": 2935951,
                    "thumbUrl": "/app/image_maker/1028528/911614/ii_UuxmTsIb8wWZ7Gb4.png",
                    "typeId": 1
                },
                {
                    "itmId": 2935952,
                    "thumbUrl": "/app/image_maker/1028528/911614/ii_uKJjNMhRfB9adV4P.png",
                    "typeId": 1
                },
                {
                    "itmId": 2935953,
                    "thumbUrl": "/app/image_maker/1028528/911614/ii_hOvpiFeMQHvyPyns.png",
                    "typeId": 1
                },
                {
                    "itmId": 2935954,
                    "thumbUrl": "/app/image_maker/1028528/911614/ii_jouLpzuVggNdWtOT.png",
                    "typeId": 1
                },
                {
                    "itmId": 2935955,
                    "thumbUrl": "/app/image_maker/1028528/911614/ii_gWdq1BtLmwryfLvt.png",
                    "typeId": 1
                },
                {
                    "itmId": 2935956,
                    "thumbUrl": "/app/image_maker/1028528/911614/ii_8f6sODPTKD1wqezF.png",
                    "typeId": 1
                },
                {
                    "itmId": 2935957,
                    "thumbUrl": "/app/image_maker/1028528/911614/ii_tBCLG9TX2ZaSpkoR.png",
                    "typeId": 1
                },
                {
                    "itmId": 2935958,
                    "thumbUrl": "/app/image_maker/1028528/911614/ii_F3qtuuWzWi27Thud.png",
                    "typeId": 1
                },
                {
                    "itmId": 2935959,
                    "thumbUrl": "/app/image_maker/1028528/911614/ii_PPJzx6OAANA1SlAb.png",
                    "typeId": 1
                },
                {
                    "itmId": 2935960,
                    "thumbUrl": "/app/image_maker/1028528/911614/ii_pLNGZ032dceCOPvT.png",
                    "typeId": 1
                },
                {
                    "itmId": 2935961,
                    "thumbUrl": "/app/image_maker/1028528/911614/ii_dY6X27xILPAQVdKt.png",
                    "typeId": 1
                },
                {
                    "itmId": 2936006,
                    "thumbUrl": "/app/image_maker/1028528/911614/ii_F6wkspkrydLrSxlJ.png",
                    "typeId": 1
                },
                {
                    "itmId": 2936007,
                    "thumbUrl": "/app/image_maker/1028528/911614/ii_5zSK6bs81seBGAYO.png",
                    "typeId": 1
                },
                {
                    "itmId": 2936008,
                    "thumbUrl": "/app/image_maker/1028528/911614/ii_ZgCYXn26KCESRu4j.png",
                    "typeId": 1
                },
                {
                    "itmId": 2936009,
                    "thumbUrl": "/app/image_maker/1028528/911614/ii_Q9CxRAV7Lp0WFzUN.png",
                    "typeId": 1
                },
                {
                    "itmId": 2936010,
                    "thumbUrl": "/app/image_maker/1028528/911614/ii_uOnLFOJYHkukzsp4.png",
                    "typeId": 1
                },
                {
                    "itmId": 2936011,
                    "thumbUrl": "/app/image_maker/1028528/911614/ii_vM9LASyn1GmWCtSN.png",
                    "typeId": 1
                },
                {
                    "itmId": 2936012,
                    "thumbUrl": "/app/image_maker/1028528/911614/ii_Ekr6LPvATzJuLJEO.png",
                    "typeId": 1
                },
                {
                    "itmId": 2936013,
                    "thumbUrl": "/app/image_maker/1028528/911614/ii_qfFRIUaSg5qlmoK3.png",
                    "typeId": 1
                },
                {
                    "itmId": 2936223,
                    "thumbUrl": "/app/image_maker/1028528/911614/ii_5LOYWOa1VpbddBQ9.png",
                    "typeId": 1
                },
                {
                    "itmId": 2936224,
                    "thumbUrl": "/app/image_maker/1028528/911614/ii_prGm2g1YBXh01KFs.png",
                    "typeId": 1
                },
                {
                    "itmId": 2936225,
                    "thumbUrl": "/app/image_maker/1028528/911614/ii_pt632iUbEOtze1sT.png",
                    "typeId": 1
                },
                {
                    "itmId": 2936226,
                    "thumbUrl": "/app/image_maker/1028528/911614/ii_ljXKzQYKMuzwycyp.png",
                    "typeId": 1
                },
                {
                    "itmId": 2936227,
                    "thumbUrl": "/app/image_maker/1028528/911614/ii_EIIcPThr4WzMlZ6X.png",
                    "typeId": 1
                },
                {
                    "itmId": 2936228,
                    "thumbUrl": "/app/image_maker/1028528/911614/ii_10Bh2n85752NcTqq.png",
                    "typeId": 1
                },
                {
                    "itmId": 2936229,
                    "thumbUrl": "/app/image_maker/1028528/911614/ii_QR6HHQGOy9PEU9Ne.png",
                    "typeId": 1
                },
                {
                    "itmId": 2936230,
                    "thumbUrl": "/app/image_maker/1028528/911614/ii_LOWph2T7c0ryCCJi.png",
                    "typeId": 1
                },
                {
                    "itmId": 2936231,
                    "thumbUrl": "/app/image_maker/1028528/911614/ii_BfKS1C4dSy5RsisE.png",
                    "typeId": 1
                },
                {
                    "itmId": 2936232,
                    "thumbUrl": "/app/image_maker/1028528/911614/ii_0zSk9FfZfDRChTz6.png",
                    "typeId": 1
                },
                {
                    "itmId": 2936336,
                    "thumbUrl": "/app/image_maker/1028528/911614/ii_LPzZmlC4fVfOJqw7.png",
                    "typeId": 1
                },
                {
                    "itmId": 2936337,
                    "thumbUrl": "/app/image_maker/1028528/911614/ii_ZxzEBUkLPaxpMV7w.png",
                    "typeId": 1
                },
                {
                    "itmId": 2936338,
                    "thumbUrl": "/app/image_maker/1028528/911614/ii_sAhZEahRoKz7tCQb.png",
                    "typeId": 1
                },
                {
                    "itmId": 2936339,
                    "thumbUrl": "/app/image_maker/1028528/911614/ii_PCPEP8ujoN9g7ixB.png",
                    "typeId": 1
                },
                {
                    "itmId": 2936340,
                    "thumbUrl": "/app/image_maker/1028528/911614/ii_v0vQMQpcg8nHEJVs.png",
                    "typeId": 1
                },
                {
                    "itmId": 2936341,
                    "thumbUrl": "/app/image_maker/1028528/911614/ii_uZhyvSXaZaWCUsJl.png",
                    "typeId": 1
                },
                {
                    "itmId": 2936342,
                    "thumbUrl": "/app/image_maker/1028528/911614/ii_zXtnUwVy1Ww592bQ.png",
                    "typeId": 1
                },
                {
                    "itmId": 2936343,
                    "thumbUrl": "/app/image_maker/1028528/911614/ii_kuHZpqEaZZ8AzKGy.png",
                    "typeId": 1
                },
                {
                    "itmId": 2936344,
                    "thumbUrl": "/app/image_maker/1028528/911614/ii_hSlIlUtiguNwHkPR.png",
                    "typeId": 1
                },
                {
                    "itmId": 2936345,
                    "thumbUrl": "/app/image_maker/1028528/911614/ii_oz79Q9uk6GxdF1Uq.png",
                    "typeId": 1
                },
                {
                    "itmId": 2936641,
                    "thumbUrl": "/app/image_maker/1028528/911614/ii_AvHgIadaFobt1iQO.png",
                    "typeId": 1
                },
                {
                    "itmId": 2936642,
                    "thumbUrl": "/app/image_maker/1028528/911614/ii_R3byZMHaUoQViItN.png",
                    "typeId": 1
                },
                {
                    "itmId": 2936643,
                    "thumbUrl": "/app/image_maker/1028528/911614/ii_dDjwYLtCRJKUJQWz.png",
                    "typeId": 1
                },
                {
                    "itmId": 2936644,
                    "thumbUrl": "/app/image_maker/1028528/911614/ii_8TR24TFCkWBRWdfN.png",
                    "typeId": 1
                },
                {
                    "itmId": 2936645,
                    "thumbUrl": "/app/image_maker/1028528/911614/ii_wCVuLW1iLT0gOXgP.png",
                    "typeId": 1
                },
                {
                    "itmId": 2936710,
                    "thumbUrl": "/app/image_maker/1028528/911614/ii_byGFEOFFRXg8tB7Q.png",
                    "typeId": 1
                },
                {
                    "itmId": 2936711,
                    "thumbUrl": "/app/image_maker/1028528/911614/ii_57kzwbULAZkaNryl.png",
                    "typeId": 1
                },
                {
                    "itmId": 2936712,
                    "thumbUrl": "/app/image_maker/1028528/911614/ii_qTHCJ1v43LQF8Q7N.png",
                    "typeId": 1
                },
                {
                    "itmId": 2936713,
                    "thumbUrl": "/app/image_maker/1028528/911614/ii_UJsX7vfzNTha5zIS.png",
                    "typeId": 1
                },
                {
                    "itmId": 2936714,
                    "thumbUrl": "/app/image_maker/1028528/911614/ii_NH0jYqcTjVL6i7uV.png",
                    "typeId": 1
                },
                {
                    "itmId": 2936750,
                    "thumbUrl": "/app/image_maker/1028528/911614/ii_XFFtzicIcu7pZncD.png",
                    "typeId": 1
                },
                {
                    "itmId": 2936751,
                    "thumbUrl": "/app/image_maker/1028528/911614/ii_LzFAelozgX6VA1El.png",
                    "typeId": 1
                },
                {
                    "itmId": 2936752,
                    "thumbUrl": "/app/image_maker/1028528/911614/ii_L6ZKeamIkj9sbHQr.png",
                    "typeId": 1
                },
                {
                    "itmId": 2936753,
                    "thumbUrl": "/app/image_maker/1028528/911614/ii_okeREeKKLgv701T8.png",
                    "typeId": 1
                },
                {
                    "itmId": 2936754,
                    "thumbUrl": "/app/image_maker/1028528/911614/ii_E7CnWcDtChvu4boB.png",
                    "typeId": 1
                },
                {
                    "itmId": 2936784,
                    "thumbUrl": "/app/image_maker/1028528/911614/ii_QIWQes4hYRIASFBn.png",
                    "typeId": 1
                },
                {
                    "itmId": 2936785,
                    "thumbUrl": "/app/image_maker/1028528/911614/ii_PvtwL5vTWqGAfdys.png",
                    "typeId": 1
                },
                {
                    "itmId": 2936786,
                    "thumbUrl": "/app/image_maker/1028528/911614/ii_H7uezy1IIjtjQU3Q.png",
                    "typeId": 1
                },
                {
                    "itmId": 2936787,
                    "thumbUrl": "/app/image_maker/1028528/911614/ii_eargCBxf7piRUvtE.png",
                    "typeId": 1
                },
                {
                    "itmId": 2936788,
                    "thumbUrl": "/app/image_maker/1028528/911614/ii_URzAifRhQYPABdYn.png",
                    "typeId": 1
                },
                {
                    "itmId": 2936841,
                    "thumbUrl": "/app/image_maker/1028528/911614/ii_KF8eYY0mzsfyLaQz.png",
                    "typeId": 1
                },
                {
                    "itmId": 2936842,
                    "thumbUrl": "/app/image_maker/1028528/911614/ii_MwLTsvwXQYGzTBLz.png",
                    "typeId": 1
                },
                {
                    "itmId": 2936843,
                    "thumbUrl": "/app/image_maker/1028528/911614/ii_qi6bb0CsEgrnfv0h.png",
                    "typeId": 1
                },
                {
                    "itmId": 2936844,
                    "thumbUrl": "/app/image_maker/1028528/911614/ii_5i2Rxj79cuvXoOuQ.png",
                    "typeId": 1
                },
                {
                    "itmId": 2936845,
                    "thumbUrl": "/app/image_maker/1028528/911614/ii_fdr70rqC4KhNfyBK.png",
                    "typeId": 1
                },
                {
                    "itmId": 2936935,
                    "thumbUrl": "/app/image_maker/1028528/911614/ii_9YAxMvoHm5KKOAR6.png",
                    "typeId": 1
                },
                {
                    "itmId": 2936936,
                    "thumbUrl": "/app/image_maker/1028528/911614/ii_AwMFKJ5xKkxIEwdJ.png",
                    "typeId": 1
                },
                {
                    "itmId": 2936937,
                    "thumbUrl": "/app/image_maker/1028528/911614/ii_T4pJJate91SYKCIb.png",
                    "typeId": 1
                },
                {
                    "itmId": 2936938,
                    "thumbUrl": "/app/image_maker/1028528/911614/ii_fRx0CQmpyWOtdhAw.png",
                    "typeId": 1
                },
                {
                    "itmId": 2936939,
                    "thumbUrl": "/app/image_maker/1028528/911614/ii_lacVjPTQIf8kO0LH.png",
                    "typeId": 1
                },
                {
                    "itmId": 2937667,
                    "thumbUrl": "/app/image_maker/1028528/911614/ii_xFqmngsABXLLWt9e.png",
                    "typeId": 1
                },
                {
                    "itmId": 2937668,
                    "thumbUrl": "/app/image_maker/1028528/911614/ii_KyAU2H5BP5zlZfxB.png",
                    "typeId": 1
                },
                {
                    "itmId": 2937669,
                    "thumbUrl": "/app/image_maker/1028528/911614/ii_wO9lnipNW5jQzcBz.png",
                    "typeId": 1
                },
                {
                    "itmId": 2937670,
                    "thumbUrl": "/app/image_maker/1028528/911614/ii_t7hkzrEt16u2nEvC.png",
                    "typeId": 1
                },
                {
                    "itmId": 2937671,
                    "thumbUrl": "/app/image_maker/1028528/911614/ii_YBFmct5l8xGtV5ga.png",
                    "typeId": 1
                },
                {
                    "itmId": 2937672,
                    "thumbUrl": "/app/image_maker/1028528/911614/ii_rsAFu4iBVZr8Ikbp.png",
                    "typeId": 1
                },
                {
                    "itmId": 2937673,
                    "thumbUrl": "/app/image_maker/1028528/911614/ii_q8de87rHOOvGPPzT.png",
                    "typeId": 1
                },
                {
                    "itmId": 2937674,
                    "thumbUrl": "/app/image_maker/1028528/911614/ii_QUqKVDz8oT0O2Tj7.png",
                    "typeId": 1
                },
                {
                    "itmId": 2937675,
                    "thumbUrl": "/app/image_maker/1028528/911614/ii_V4Q00mHjZAASLF9S.png",
                    "typeId": 1
                },
                {
                    "itmId": 2937676,
                    "thumbUrl": "/app/image_maker/1028528/911614/ii_4FrIuEAGLzu41FgZ.png",
                    "typeId": 1
                },
                {
                    "itmId": 2937814,
                    "thumbUrl": "/app/image_maker/1028528/911614/ii_Gw8wvO9rAfN1VKQ5.png",
                    "typeId": 1
                },
                {
                    "itmId": 2937815,
                    "thumbUrl": "/app/image_maker/1028528/911614/ii_UKTsCbaX83e1tDpp.png",
                    "typeId": 1
                },
                {
                    "itmId": 2937816,
                    "thumbUrl": "/app/image_maker/1028528/911614/ii_I0Wvm47utixrtBCG.png",
                    "typeId": 1
                },
                {
                    "itmId": 2937817,
                    "thumbUrl": "/app/image_maker/1028528/911614/ii_ZmzkdIANYf7SyuNP.png",
                    "typeId": 1
                },
                {
                    "itmId": 2937818,
                    "thumbUrl": "/app/image_maker/1028528/911614/ii_hAvEZIH42Qzo0UEQ.png",
                    "typeId": 1
                },
                {
                    "itmId": 2937819,
                    "thumbUrl": "/app/image_maker/1028528/911614/ii_EsZCU4e6qFVG01sR.png",
                    "typeId": 1
                },
                {
                    "itmId": 2937820,
                    "thumbUrl": "/app/image_maker/1028528/911614/ii_kyDjMkpv5A0w4VD5.png",
                    "typeId": 1
                },
                {
                    "itmId": 2937821,
                    "thumbUrl": "/app/image_maker/1028528/911614/ii_DlKcBYZZbxagSvBI.png",
                    "typeId": 1
                },
                {
                    "itmId": 2937822,
                    "thumbUrl": "/app/image_maker/1028528/911614/ii_U8rzazjySXHQ4X6d.png",
                    "typeId": 1
                },
                {
                    "itmId": 2937823,
                    "thumbUrl": "/app/image_maker/1028528/911614/ii_VBIKDOpPnOeCb9A4.png",
                    "typeId": 1
                },
                {
                    "itmId": 2937951,
                    "thumbUrl": "/app/image_maker/1028528/911614/ii_z1dTFCnMwjYyh9Xy.png",
                    "typeId": 1
                },
                {
                    "itmId": 2937952,
                    "thumbUrl": "/app/image_maker/1028528/911614/ii_6nKCMFDwKkT8txw4.png",
                    "typeId": 1
                },
                {
                    "itmId": 2937953,
                    "thumbUrl": "/app/image_maker/1028528/911614/ii_NPkyfhmVqmAP80w5.png",
                    "typeId": 1
                },
                {
                    "itmId": 2937954,
                    "thumbUrl": "/app/image_maker/1028528/911614/ii_Z4Ha1R8GyAso6HwJ.png",
                    "typeId": 1
                },
                {
                    "itmId": 2937955,
                    "thumbUrl": "/app/image_maker/1028528/911614/ii_QbLH7sU8eM45znRp.png",
                    "typeId": 1
                },
                {
                    "itmId": 2937956,
                    "thumbUrl": "/app/image_maker/1028528/911614/ii_3LVBpCBQ0uuqFJGP.png",
                    "typeId": 1
                },
                {
                    "itmId": 2937957,
                    "thumbUrl": "/app/image_maker/1028528/911614/ii_QihSrFxQ8aGuFQcs.png",
                    "typeId": 1
                },
                {
                    "itmId": 2937958,
                    "thumbUrl": "/app/image_maker/1028528/911614/ii_65pDsRfMbguideT8.png",
                    "typeId": 1
                },
                {
                    "itmId": 2937959,
                    "thumbUrl": "/app/image_maker/1028528/911614/ii_SEULrWdw8D8EKU3y.png",
                    "typeId": 1
                },
                {
                    "itmId": 2937960,
                    "thumbUrl": "/app/image_maker/1028528/911614/ii_VfEFsmdV0CoSA0ui.png",
                    "typeId": 1
                }
            ],
            "rules": [],
            "defItmId": 2935947
        }
    ],
    "cpList": {
        "l909373": [
            {
                "cId": 1937622,
                "cd": "#FFFFFF"
            },
            {
                "cId": 1937624,
                "cd": "#FF7777"
            },
            {
                "cId": 1937626,
                "cd": "#FFC77D"
            },
            {
                "cId": 1937627,
                "cd": "#FFFA55"
            },
            {
                "cId": 1937628,
                "cd": "#57FF6B"
            },
            {
                "cId": 1937630,
                "cd": "#5FF8FF"
            },
            {
                "cId": 1937631,
                "cd": "#6A6EFF"
            },
            {
                "cId": 1937633,
                "cd": "#D171FF"
            },
            {
                "cId": 1937634,
                "cd": "#FF73E8"
            },
            {
                "cId": 1937635,
                "cd": "#ABABAB"
            },
            {
                "cId": 1937636,
                "cd": "#000000"
            },
            {
                "cId": 1937638,
                "cd": "#856C65"
            }
        ],
        "l910856": [
            {
                "cId": 1940093,
                "cd": "#6B6B6B"
            },
            {
                "cId": 1940099,
                "cd": "#78C9FF"
            },
            {
                "cId": 1940101,
                "cd": "#FF7CF0"
            },
            {
                "cId": 1940102,
                "cd": "#FDFF87"
            },
            {
                "cId": 1940451,
                "cd": "#A8FF7E"
            },
            {
                "cId": 1940453,
                "cd": "#FF7171"
            },
            {
                "cId": 1940454,
                "cd": "#E967FF"
            },
            {
                "cId": 1940455,
                "cd": "#8E7474"
            },
            {
                "cId": 1940475,
                "cd": "#FFFFFF"
            }
        ],
        "l911155": [
            {
                "cId": 1940640,
                "cd": "#FFFFFF"
            }
        ],
        "l911614": [
            {
                "cId": 1941732,
                "cd": "#FFFFFF"
            }
        ],
        "l912396": [
            {
                "cId": 1943214,
                "cd": "#FFFFFF"
            }
        ],
        "l912398": [
            {
                "cId": 1943216,
                "cd": "#FFFFFF"
            }
        ],
        "l912400": [
            {
                "cId": 1943218,
                "cd": "#FFFFFF"
            }
        ]
    },
    "lyrList": {
        "1014961": 2,
        "1016599": 4,
        "1016925": 5,
        "1017458": 1,
        "1018338": 6,
        "1018340": 8,
        "1018342": 7
    },
    "zeroConf": {
        "909373": {
            "itmId": 2931090,
            "cId": 1937622,
            "xCnt": 0,
            "yCnt": 0,
            "spCnt": 0,
            "sNo": 0,
            "rotaCnt": 0
        },
        "910856": {
            "itmId": 2934480,
            "cId": 1940093,
            "xCnt": 0,
            "yCnt": 0,
            "spCnt": 0,
            "sNo": 0,
            "rotaCnt": 0
        },
        "911155": {
            "itmId": 2935020,
            "cId": 1940640,
            "xCnt": 0,
            "yCnt": 0,
            "spCnt": 0,
            "sNo": 0,
            "rotaCnt": 0
        },
        "911614": {
            "itmId": 2935947,
            "cId": 1941732,
            "xCnt": 0,
            "yCnt": 0,
            "spCnt": 0,
            "sNo": 0,
            "rotaCnt": 0
        },
        "912396": {
            "itmId": 2938096,
            "cId": 1943214,
            "xCnt": 0,
            "yCnt": 0,
            "spCnt": 0,
            "sNo": 0,
            "rotaCnt": 0
        },
        "912398": {
            "itmId": 2938099,
            "cId": 1943216,
            "xCnt": 0,
            "yCnt": 0,
            "spCnt": 0,
            "sNo": 0,
            "rotaCnt": 0
        },
        "912400": {
            "itmId": 0,
            "cId": 1943218,
            "xCnt": 0,
            "yCnt": 0,
            "spCnt": 0,
            "sNo": 0,
            "rotaCnt": 0
        }
    },
    "ruleList": {}
}